README.md
setup.py
DEBKS.egg-info/PKG-INFO
DEBKS.egg-info/SOURCES.txt
DEBKS.egg-info/dependency_links.txt
DEBKS.egg-info/entry_points.txt
DEBKS.egg-info/requires.txt
DEBKS.egg-info/top_level.txt
debks/DEBKS_main.py
debks/__init__.py
debks/anno.py
debks/count.py
debks/dec.py
debks/merge.py
debks/rMATs.py
debks/rMATs_paired.py
debks/version.py